{".class": "MypyFile", "_fullname": "dmate.section", "is_partial_stub_package": false, "is_stub": false, "names": {".class": "SymbolTable", "List": {".class": "SymbolTableNode", "cross_ref": "typing.List", "kind": "Gdef"}, "Path": {".class": "SymbolTableNode", "cross_ref": "pathlib.Path", "kind": "Gdef"}, "PurePath": {".class": "SymbolTableNode", "cross_ref": "pathlib.PurePath", "kind": "Gdef"}, "Script": {".class": "SymbolTableNode", "cross_ref": "dmate.script.Script", "kind": "Gdef"}, "Section": {".class": "SymbolTableNode", "kind": "Gdef", "node": {".class": "TypeInfo", "_promote": null, "abstract_attributes": [], "bases": ["builtins.object"], "declared_metaclass": null, "defn": {".class": "ClassDef", "fullname": "dmate.section.Section", "name": "Section", "type_vars": []}, "flags": [], "fullname": "dmate.section.Section", "metaclass_type": null, "metadata": {}, "module_name": "dmate.section", "mro": ["dmate.section.Section", "builtins.object"], "names": {".class": "SymbolTable", "__delitem__": {".class": "SymbolTableNode", "kind": "Mdef", "node": {".class": "FuncDef", "arg_kinds": [0, 0], "arg_names": ["self", "step_i"], "flags": [], "fullname": "dmate.section.Section.__delitem__", "name": "__delitem__", "type": null}}, "__getitem__": {".class": "SymbolTableNode", "kind": "Mdef", "node": {".class": "FuncDef", "arg_kinds": [0, 0], "arg_names": ["self", "step_i"], "flags": [], "fullname": "dmate.section.Section.__getitem__", "name": "__getitem__", "type": {".class": "CallableType", "arg_kinds": [0, 0], "arg_names": [null, null], "arg_types": ["dmate.section.Section", "builtins.int"], "bound_args": [], "def_extras": {"first_arg": "self"}, "fallback": "builtins.function", "implicit": false, "is_ellipsis_args": false, "name": "__getitem__ of Section", "ret_type": {".class": "AnyType", "missing_import_name": null, "source_any": null, "type_of_any": 1}, "variables": []}}}, "__init__": {".class": "SymbolTableNode", "kind": "Mdef", "node": {".class": "FuncDef", "arg_kinds": [0, 1, 1, 1, 1, 1, 1, 1, 1], "arg_names": ["self", "elem", "copy", "demo_dir", "idx", "demo_idx", "title", "audio", "is_special"], "flags": [], "fullname": "dmate.section.Section.__init__", "name": "__init__", "type": {".class": "CallableType", "arg_kinds": [0, 1, 1, 1, 1, 1, 1, 1, 1], "arg_names": ["self", "elem", "copy", "demo_dir", "idx", "demo_idx", "title", "audio", "is_special"], "arg_types": ["dmate.section.Section", {".class": "AnyType", "missing_import_name": null, "source_any": null, "type_of_any": 1}, "builtins.bool", {".class": "UnionType", "items": ["builtins.str", {".class": "NoneType"}]}, "builtins.int", "builtins.int", "builtins.str", "builtins.str", "builtins.bool"], "bound_args": [], "def_extras": {"first_arg": "self"}, "fallback": "builtins.function", "implicit": false, "is_ellipsis_args": false, "name": "__init__ of Section", "ret_type": {".class": "NoneType"}, "variables": []}}}, "__iter__": {".class": "SymbolTableNode", "kind": "Mdef", "node": {".class": "FuncDef", "arg_kinds": [0], "arg_names": ["self"], "flags": [], "fullname": "dmate.section.Section.__iter__", "name": "__iter__", "type": null}}, "__len__": {".class": "SymbolTableNode", "kind": "Mdef", "node": {".class": "FuncDef", "arg_kinds": [0], "arg_names": ["self"], "flags": [], "fullname": "dmate.section.Section.__len__", "name": "__len__", "type": null}}, "__repr__": {".class": "SymbolTableNode", "kind": "Mdef", "node": {".class": "FuncDef", "arg_kinds": [0], "arg_names": ["self"], "flags": [], "fullname": "dmate.section.Section.__repr__", "name": "__repr__", "type": null}}, "__setitem__": {".class": "SymbolTableNode", "kind": "Mdef", "node": {".class": "FuncDef", "arg_kinds": [0, 0, 0], "arg_names": ["self", "step_i", "step"], "flags": [], "fullname": "dmate.section.Section.__setitem__", "name": "__setitem__", "type": {".class": "CallableType", "arg_kinds": [0, 0, 0], "arg_names": [null, null, null], "arg_types": ["dmate.section.Section", "builtins.int", "dmate.step.Step"], "bound_args": [], "def_extras": {"first_arg": "self"}, "fallback": "builtins.function", "implicit": false, "is_ellipsis_args": false, "name": "__setitem__ of Section", "ret_type": {".class": "AnyType", "missing_import_name": null, "source_any": null, "type_of_any": 1}, "variables": []}}}, "__str__": {".class": "SymbolTableNode", "kind": "Mdef", "node": {".class": "FuncDef", "arg_kinds": [0], "arg_names": ["self"], "flags": [], "fullname": "dmate.section.Section.__str__", "name": "__str__", "type": null}}, "append": {".class": "SymbolTableNode", "kind": "Mdef", "node": {".class": "FuncDef", "arg_kinds": [0, 0], "arg_names": ["self", "step"], "flags": [], "fullname": "dmate.section.Section.append", "name": "append", "type": {".class": "CallableType", "arg_kinds": [0, 0], "arg_names": ["self", "step"], "arg_types": ["dmate.section.Section", "dmate.step.Step"], "bound_args": [], "def_extras": {"first_arg": "self"}, "fallback": "builtins.function", "implicit": false, "is_ellipsis_args": false, "name": "append of Section", "ret_type": {".class": "AnyType", "missing_import_name": null, "source_any": null, "type_of_any": 1}, "variables": []}}}, "assets": {".class": "SymbolTableNode", "implicit": true, "kind": "Mdef", "node": {".class": "Var", "flags": [], "fullname": "dmate.section.Section.assets", "name": "assets", "type": {".class": "AnyType", "missing_import_name": null, "source_any": null, "type_of_any": 1}}}, "audio": {".class": "SymbolTableNode", "implicit": true, "kind": "Mdef", "node": {".class": "Var", "flags": [], "fullname": "dmate.section.Section.audio", "name": "audio", "type": {".class": "AnyType", "missing_import_name": null, "source_any": null, "type_of_any": 1}}}, "children": {".class": "SymbolTableNode", "implicit": true, "kind": "Mdef", "node": {".class": "Var", "flags": [], "fullname": "dmate.section.Section.children", "name": "children", "type": {".class": "AnyType", "missing_import_name": null, "source_any": {".class": "AnyType", "missing_import_name": null, "source_any": null, "type_of_any": 1}, "type_of_any": 7}}}, "delete_step": {".class": "SymbolTableNode", "kind": "Mdef", "node": {".class": "FuncDef", "arg_kinds": [0, 0], "arg_names": ["self", "idx"], "flags": [], "fullname": "dmate.section.Section.delete_step", "name": "delete_step", "type": {".class": "CallableType", "arg_kinds": [0, 0], "arg_names": ["self", "idx"], "arg_types": ["dmate.section.Section", "builtins.int"], "bound_args": [], "def_extras": {"first_arg": "self"}, "fallback": "builtins.function", "implicit": false, "is_ellipsis_args": false, "name": "delete_step of Section", "ret_type": {".class": "AnyType", "missing_import_name": null, "source_any": null, "type_of_any": 1}, "variables": []}}}, "demo_dir": {".class": "SymbolTableNode", "implicit": true, "kind": "Mdef", "node": {".class": "Var", "flags": [], "fullname": "dmate.section.Section.demo_dir", "name": "demo_dir", "type": {".class": "UnionType", "items": ["builtins.str", {".class": "NoneType"}]}}}, "demo_idx": {".class": "SymbolTableNode", "implicit": true, "kind": "Mdef", "node": {".class": "Var", "flags": [], "fullname": "dmate.section.Section.demo_idx", "name": "demo_idx", "type": "builtins.int"}}, "duplicate_step": {".class": "SymbolTableNode", "kind": "Mdef", "node": {".class": "FuncDef", "arg_kinds": [0, 0, 1], "arg_names": ["self", "idx", "as_pacing"], "flags": [], "fullname": "dmate.section.Section.duplicate_step", "name": "duplicate_step", "type": {".class": "CallableType", "arg_kinds": [0, 0, 1], "arg_names": ["self", "idx", "as_pacing"], "arg_types": ["dmate.section.Section", "builtins.int", "builtins.bool"], "bound_args": [], "def_extras": {"first_arg": "self"}, "fallback": "builtins.function", "implicit": false, "is_ellipsis_args": false, "name": "duplicate_step of Section", "ret_type": {".class": "AnyType", "missing_import_name": null, "source_any": null, "type_of_any": 1}, "variables": []}}}, "duplicate_tep": {".class": "SymbolTableNode", "kind": "Mdef", "node": {".class": "FuncDef", "arg_kinds": [0, 0], "arg_names": ["self", "step_i"], "flags": [], "fullname": "dmate.section.Section.duplicate_tep", "name": "duplicate_tep", "type": {".class": "CallableType", "arg_kinds": [0, 0], "arg_names": ["self", "step_i"], "arg_types": ["dmate.section.Section", "builtins.int"], "bound_args": [], "def_extras": {"first_arg": "self"}, "fallback": "builtins.function", "implicit": false, "is_ellipsis_args": false, "name": "duplicate_tep of Section", "ret_type": {".class": "AnyType", "missing_import_name": null, "source_any": null, "type_of_any": 1}, "variables": []}}}, "extend": {".class": "SymbolTableNode", "kind": "Mdef", "node": {".class": "FuncDef", "arg_kinds": [0, 0], "arg_names": ["self", "steps"], "flags": [], "fullname": "dmate.section.Section.extend", "name": "extend", "type": {".class": "CallableType", "arg_kinds": [0, 0], "arg_names": ["self", "steps"], "arg_types": ["dmate.section.Section", {".class": "Instance", "args": [{".class": "AnyType", "missing_import_name": null, "source_any": null, "type_of_any": 4}], "type_ref": "collections.deque"}], "bound_args": [], "def_extras": {"first_arg": "self"}, "fallback": "builtins.function", "implicit": false, "is_ellipsis_args": false, "name": "extend of Section", "ret_type": {".class": "AnyType", "missing_import_name": null, "source_any": null, "type_of_any": 1}, "variables": []}}}, "id": {".class": "SymbolTableNode", "implicit": true, "kind": "Mdef", "node": {".class": "Var", "flags": [], "fullname": "dmate.section.Section.id", "name": "id", "type": {".class": "AnyType", "missing_import_name": null, "source_any": null, "type_of_any": 1}}}, "idx": {".class": "SymbolTableNode", "implicit": true, "kind": "Mdef", "node": {".class": "Var", "flags": [], "fullname": "dmate.section.Section.idx", "name": "idx", "type": "builtins.int"}}, "insert_step": {".class": "SymbolTableNode", "kind": "Mdef", "node": {".class": "FuncDef", "arg_kinds": [0, 0, 1], "arg_names": ["self", "step", "before"], "flags": [], "fullname": "dmate.section.Section.insert_step", "name": "insert_step", "type": {".class": "CallableType", "arg_kinds": [0, 0, 1], "arg_names": ["self", "step", "before"], "arg_types": ["dmate.section.Section", "dmate.step.Step", {".class": "AnyType", "missing_import_name": null, "source_any": null, "type_of_any": 1}], "bound_args": [], "def_extras": {"first_arg": "self"}, "fallback": "builtins.function", "implicit": false, "is_ellipsis_args": false, "name": "insert_step of Section", "ret_type": {".class": "AnyType", "missing_import_name": null, "source_any": null, "type_of_any": 1}, "variables": []}}}, "is_special": {".class": "SymbolTableNode", "implicit": true, "kind": "Mdef", "node": {".class": "Var", "flags": [], "fullname": "dmate.section.Section.is_special", "name": "is_special", "type": "builtins.bool"}}, "iter": {".class": "SymbolTableNode", "kind": "Mdef", "node": {".class": "FuncDef", "arg_kinds": [0, 1], "arg_names": ["self", "item"], "flags": ["is_generator"], "fullname": "dmate.section.Section.iter", "name": "iter", "type": null}}, "length": {".class": "SymbolTableNode", "implicit": true, "kind": "Mdef", "node": {".class": "Var", "flags": [], "fullname": "dmate.section.Section.length", "name": "length", "type": "builtins.int"}}, "load": {".class": "SymbolTableNode", "kind": "Mdef", "node": {".class": "FuncDef", "arg_kinds": [0], "arg_names": ["self"], "flags": [], "fullname": "dmate.section.Section.load", "name": "load", "type": null}}, "loaded": {".class": "SymbolTableNode", "implicit": true, "kind": "Mdef", "node": {".class": "Var", "flags": [], "fullname": "dmate.section.Section.loaded", "name": "loaded", "type": {".class": "AnyType", "missing_import_name": null, "source_any": null, "type_of_any": 1}}}, "pop": {".class": "SymbolTableNode", "kind": "Mdef", "node": {".class": "FuncDef", "arg_kinds": [0], "arg_names": ["self"], "flags": [], "fullname": "dmate.section.Section.pop", "name": "pop", "type": null}}, "popleft": {".class": "SymbolTableNode", "kind": "Mdef", "node": {".class": "FuncDef", "arg_kinds": [0], "arg_names": ["self"], "flags": [], "fullname": "dmate.section.Section.popleft", "name": "popleft", "type": null}}, "remove_step": {".class": "SymbolTableNode", "kind": "Mdef", "node": {".class": "FuncDef", "arg_kinds": [0, 0], "arg_names": ["self", "step_i"], "flags": [], "fullname": "dmate.section.Section.remove_step", "name": "remove_step", "type": {".class": "CallableType", "arg_kinds": [0, 0], "arg_names": ["self", "step_i"], "arg_types": ["dmate.section.Section", "builtins.int"], "bound_args": [], "def_extras": {"first_arg": "self"}, "fallback": "builtins.function", "implicit": false, "is_ellipsis_args": false, "name": "remove_step of Section", "ret_type": {".class": "AnyType", "missing_import_name": null, "source_any": null, "type_of_any": 1}, "variables": []}}}, "root": {".class": "SymbolTableNode", "implicit": true, "kind": "Mdef", "node": {".class": "Var", "flags": [], "fullname": "dmate.section.Section.root", "name": "root", "type": {".class": "AnyType", "missing_import_name": null, "source_any": null, "type_of_any": 1}}}, "set_animated": {".class": "SymbolTableNode", "kind": "Mdef", "node": {".class": "FuncDef", "arg_kinds": [0, 1], "arg_names": ["self", "key"], "flags": [], "fullname": "dmate.section.Section.set_animated", "name": "set_animated", "type": {".class": "CallableType", "arg_kinds": [0, 1], "arg_names": ["self", "key"], "arg_types": ["dmate.section.Section", {".class": "UnionType", "items": ["builtins.str", {".class": "NoneType"}]}], "bound_args": [], "def_extras": {"first_arg": "self"}, "fallback": "builtins.function", "implicit": false, "is_ellipsis_args": false, "name": "set_animated of Section", "ret_type": {".class": "AnyType", "missing_import_name": null, "source_any": null, "type_of_any": 1}, "variables": []}}}, "set_audio": {".class": "SymbolTableNode", "kind": "Mdef", "node": {".class": "FuncDef", "arg_kinds": [0, 0], "arg_names": ["self", "soundbite"], "flags": [], "fullname": "dmate.section.Section.set_audio", "name": "set_audio", "type": {".class": "CallableType", "arg_kinds": [0, 0], "arg_names": ["self", "soundbite"], "arg_types": ["dmate.section.Section", "dmate.audio.SoundBite"], "bound_args": [], "def_extras": {"first_arg": "self"}, "fallback": "builtins.function", "implicit": false, "is_ellipsis_args": false, "name": "set_audio of Section", "ret_type": {".class": "AnyType", "missing_import_name": null, "source_any": null, "type_of_any": 1}, "variables": []}}}, "set_guided": {".class": "SymbolTableNode", "kind": "Mdef", "node": {".class": "FuncDef", "arg_kinds": [0], "arg_names": ["self"], "flags": [], "fullname": "dmate.section.Section.set_guided", "name": "set_guided", "type": null}}, "set_step_instructions": {".class": "SymbolTableNode", "kind": "Mdef", "node": {".class": "FuncDef", "arg_kinds": [0, 0, 0], "arg_names": ["self", "ci", "tp"], "flags": [], "fullname": "dmate.section.Section.set_step_instructions", "name": "set_step_instructions", "type": {".class": "CallableType", "arg_kinds": [0, 0, 0], "arg_names": ["self", "ci", "tp"], "arg_types": ["dmate.section.Section", "builtins.str", "builtins.str"], "bound_args": [], "def_extras": {"first_arg": "self"}, "fallback": "builtins.function", "implicit": false, "is_ellipsis_args": false, "name": "set_step_instructions of Section", "ret_type": {".class": "AnyType", "missing_import_name": null, "source_any": null, "type_of_any": 1}, "variables": []}}}, "steps": {".class": "SymbolTableNode", "implicit": true, "kind": "Mdef", "node": {".class": "Var", "flags": ["explicit_self_type", "is_ready"], "fullname": "dmate.section.Section.steps", "name": "steps", "type": {".class": "Instance", "args": ["dmate.step.Step"], "type_ref": "builtins.list"}}}, "title": {".class": "SymbolTableNode", "implicit": true, "kind": "Mdef", "node": {".class": "Var", "flags": [], "fullname": "dmate.section.Section.title", "name": "title", "type": "builtins.str"}}}, "tuple_type": null, "type_vars": [], "typeddict_type": null}}, "SectionIterator": {".class": "SymbolTableNode", "kind": "Gdef", "node": {".class": "TypeInfo", "_promote": null, "abstract_attributes": [], "bases": ["builtins.object"], "declared_metaclass": null, "defn": {".class": "ClassDef", "fullname": "dmate.section.SectionIterator", "name": "SectionIterator", "type_vars": []}, "flags": [], "fullname": "dmate.section.SectionIterator", "metaclass_type": null, "metadata": {}, "module_name": "dmate.section", "mro": ["dmate.section.SectionIterator", "builtins.object"], "names": {".class": "SymbolTable", "__init__": {".class": "SymbolTableNode", "kind": "Mdef", "node": {".class": "FuncDef", "arg_kinds": [0, 0], "arg_names": ["self", "sect"], "flags": [], "fullname": "dmate.section.SectionIterator.__init__", "name": "__init__", "type": null}}, "__iter__": {".class": "SymbolTableNode", "kind": "Mdef", "node": {".class": "FuncDef", "arg_kinds": [0], "arg_names": ["self"], "flags": [], "fullname": "dmate.section.SectionIterator.__iter__", "name": "__iter__", "type": null}}, "__next__": {".class": "SymbolTableNode", "kind": "Mdef", "node": {".class": "FuncDef", "arg_kinds": [0], "arg_names": ["self"], "flags": [], "fullname": "dmate.section.SectionIterator.__next__", "name": "__next__", "type": null}}, "idx": {".class": "SymbolTableNode", "implicit": true, "kind": "Mdef", "node": {".class": "Var", "flags": [], "fullname": "dmate.section.SectionIterator.idx", "name": "idx", "type": {".class": "AnyType", "missing_import_name": null, "source_any": null, "type_of_any": 1}}}, "len": {".class": "SymbolTableNode", "implicit": true, "kind": "Mdef", "node": {".class": "Var", "flags": [], "fullname": "dmate.section.SectionIterator.len", "name": "len", "type": {".class": "AnyType", "missing_import_name": null, "source_any": null, "type_of_any": 1}}}, "steps": {".class": "SymbolTableNode", "implicit": true, "kind": "Mdef", "node": {".class": "Var", "flags": [], "fullname": "dmate.section.SectionIterator.steps", "name": "steps", "type": {".class": "AnyType", "missing_import_name": null, "source_any": null, "type_of_any": 1}}}}, "tuple_type": null, "type_vars": [], "typeddict_type": null}}, "SoundBite": {".class": "SymbolTableNode", "cross_ref": "dmate.audio.SoundBite", "kind": "Gdef"}, "Step": {".class": "SymbolTableNode", "cross_ref": "dmate.step.Step", "kind": "Gdef"}, "Tuple": {".class": "SymbolTableNode", "cross_ref": "typing.Tuple", "kind": "Gdef"}, "__doc__": {".class": "SymbolTableNode", "kind": "Gdef", "node": {".class": "Var", "flags": ["is_ready"], "fullname": "dmate.section.__doc__", "name": "__doc__", "type": "builtins.str"}}, "__file__": {".class": "SymbolTableNode", "kind": "Gdef", "node": {".class": "Var", "flags": ["is_ready"], "fullname": "dmate.section.__file__", "name": "__file__", "type": "builtins.str"}}, "__name__": {".class": "SymbolTableNode", "kind": "Gdef", "node": {".class": "Var", "flags": ["is_ready"], "fullname": "dmate.section.__name__", "name": "__name__", "type": "builtins.str"}}, "__package__": {".class": "SymbolTableNode", "kind": "Gdef", "node": {".class": "Var", "flags": ["is_ready"], "fullname": "dmate.section.__package__", "name": "__package__", "type": "builtins.str"}}, "deepcopy": {".class": "SymbolTableNode", "cross_ref": "copy.deepcopy", "kind": "Gdef"}, "deque": {".class": "SymbolTableNode", "cross_ref": "collections.deque", "kind": "Gdef"}, "shutil": {".class": "SymbolTableNode", "cross_ref": "shutil", "kind": "Gdef"}, "timefunc": {".class": "SymbolTableNode", "cross_ref": "etc.utils.timefunc", "kind": "Gdef"}, "uuid4": {".class": "SymbolTableNode", "cross_ref": "uuid.uuid4", "kind": "Gdef"}}, "path": "c:\\Users\\Jess\\Documents\\impres-utils\\src\\dmate\\section.py"}